MetDL/__init__.py
MetDL/data_reader/__init__.py
MetDL/data_reader/data_reader.py
MetDL/data_reader/grib2/__init__.py
MetDL/data_reader/grib2/gdaps_kim_reader.py
MetDL/data_reader/grib2/gdaps_reader.py
MetDL/data_reader/grib2/grib2_reader.py
MetDL/data_reader/grib2/ldpas_reader.py
MetDL/data_reader/netcdf/__init__.py
MetDL/data_reader/netcdf/gk2a_reader.py
MetDL/data_reader/netcdf/himawari_reader.py
MetDL/data_reader/netcdf/netcdf_reader.py
MetDL/data_reader/radar/__init__.py
MetDL/data_reader/radar/radar_cmp_reader.py
MetDL/data_reader/radar/radar_netcdf_reader.py
MetDL/data_reader/radar/radar_reader.py
MetDL/dataloader/__init__.py
MetDL/dataloader/dataloader.py
MetDL/dataset/__init__.py
MetDL/dataset/dataset.py
MetDL/metadata/META_DAPS_ABBR_INDEX_LEVEL_Table.yaml
MetDL/metadata/META_GK2A_AMI_L1B_calibration_table.xlsx
MetDL/utils/__init__.py
MetDL/utils/config.py
MetDL/utils/geotest.py
MetDL-2.2.1.dist-info/METADATA
MetDL-2.2.1.dist-info/WHEEL
MetDL-2.2.1.dist-info/top_level.txt
MetDL-2.2.1.dist-info/RECORD
